scapi/__init__.py
scapi/event/base.py
scapi/event/cloud.py
scapi/event/temporal.py
scapi/sites/activity.py
scapi/sites/asset.py
scapi/sites/base.py
scapi/sites/classroom.py
scapi/sites/comment.py
scapi/sites/forum.py
scapi/sites/mainpage.py
scapi/sites/other.py
scapi/sites/project.py
scapi/sites/session.py
scapi/sites/studio.py
scapi/sites/user.py
scapi/utils/activity_types.py
scapi/utils/client.py
scapi/utils/common.py
scapi/utils/config.py
scapi/utils/error.py
scapi/utils/file.py
scapi/utils/types.py
scapi-3.2.1.dist-info/licenses/LICENSE
scapi-3.2.1.dist-info/METADATA
scapi-3.2.1.dist-info/WHEEL
scapi-3.2.1.dist-info/top_level.txt
scapi-3.2.1.dist-info/RECORD
